{"Version": 1651437075662, "Subject": "2548632c-60e9-582a-9701-4fb8b26cfaf6", "NewPlayerExperienceFinished": true, "QueueSkills": {"competitive": {"TotalGamesNeededForRating": 0, "TotalGamesNeededForLeaderboard": 0, "CurrentSeasonGamesNeededForRating": 1, "SeasonalInfoBySeasonID": {"46ea6166-4573-1128-9cea-60a15640059b": {"SeasonID": "46ea6166-4573-1128-9cea-60a15640059b", "NumberOfWins": 18, "NumberOfWinsWithPlacements": 21, "NumberOfGames": 36, "Rank": 14, "CapstoneWins": 0, "LeaderboardRank": 0, "CompetitiveTier": 14, "RankedRating": 1474, "WinsByTier": {"0": 3, "11": 1, "12": 4, "13": 3, "14": 10}, "GamesNeededForRating": 0, "TotalWinsNeededForRank": 0}, "4cb622e1-4244-6da3-7276-8daaf1c01be2": {"SeasonID": "4cb622e1-4244-6da3-7276-8daaf1c01be2", "NumberOfWins": 17, "NumberOfWinsWithPlacements": 18, "NumberOfGames": 31, "Rank": 15, "CapstoneWins": 0, "LeaderboardRank": 0, "CompetitiveTier": 15, "RankedRating": 33, "WinsByTier": {"0": 1, "11": 1, "13": 8, "14": 6, "15": 2}, "GamesNeededForRating": 0, "TotalWinsNeededForRank": 0}, "52e9749a-429b-7060-99fe-4595426a0cf7": {"SeasonID": "52e9749a-429b-7060-99fe-4595426a0cf7", "NumberOfWins": 4, "NumberOfWinsWithPlacements": 4, "NumberOfGames": 8, "Rank": 0, "CapstoneWins": 0, "LeaderboardRank": 0, "CompetitiveTier": 12, "RankedRating": 75, "WinsByTier": {"12": 4}, "GamesNeededForRating": 0, "TotalWinsNeededForRank": 5}, "97b6e739-44cc-ffa7-49ad-398ba502ceb0": {"SeasonID": "97b6e739-44cc-ffa7-49ad-398ba502ceb0", "NumberOfWins": 1, "NumberOfWinsWithPlacements": 4, "NumberOfGames": 5, "Rank": 0, "CapstoneWins": 0, "LeaderboardRank": 0, "CompetitiveTier": 12, "RankedRating": 50, "WinsByTier": {"0": 3, "12": 1}, "GamesNeededForRating": 0, "TotalWinsNeededForRank": 8}, "a16955a5-4ad0-f761-5e9e-389df1c892fb": {"SeasonID": "a16955a5-4ad0-f761-5e9e-389df1c892fb", "NumberOfWins": 8, "NumberOfWinsWithPlacements": 8, "NumberOfGames": 16, "Rank": 0, "CapstoneWins": 0, "LeaderboardRank": 0, "CompetitiveTier": 16, "RankedRating": 0, "WinsByTier": {"15": 4, "16": 4}, "GamesNeededForRating": 0, "TotalWinsNeededForRank": 1}, "d929bc38-4ab6-7da4-94f0-ee84f8ac141e": {"SeasonID": "d929bc38-4ab6-7da4-94f0-ee84f8ac141e", "NumberOfWins": 18, "NumberOfWinsWithPlacements": 18, "NumberOfGames": 34, "Rank": 15, "CapstoneWins": 0, "LeaderboardRank": 0, "CompetitiveTier": 15, "RankedRating": 16, "WinsByTier": {"11": 3, "12": 1, "13": 7, "14": 6, "15": 1}, "GamesNeededForRating": 0, "TotalWinsNeededForRank": 0}}}, "deathmatch": {"TotalGamesNeededForRating": 0, "TotalGamesNeededForLeaderboard": 0, "CurrentSeasonGamesNeededForRating": 0, "SeasonalInfoBySeasonID": {"2a27e5d2-4d30-c9e2-b15a-93b8909a442c": {"SeasonID": "2a27e5d2-4d30-c9e2-b15a-93b8909a442c", "NumberOfWins": 0, "NumberOfWinsWithPlacements": 3, "NumberOfGames": 26, "Rank": 0, "CapstoneWins": 0, "LeaderboardRank": 0, "CompetitiveTier": 0, "RankedRating": 0, "WinsByTier": {"0": 3}, "GamesNeededForRating": 0, "TotalWinsNeededForRank": 9}, "3e47230a-463c-a301-eb7d-67bb60357d4f": {"SeasonID": "3e47230a-463c-a301-eb7d-67bb60357d4f", "NumberOfWins": 0, "NumberOfWinsWithPlacements": 3, "NumberOfGames": 45, "Rank": 0, "CapstoneWins": 0, "LeaderboardRank": 0, "CompetitiveTier": 0, "RankedRating": 0, "WinsByTier": {"0": 3}, "GamesNeededForRating": 0, "TotalWinsNeededForRank": 9}, "46ea6166-4573-1128-9cea-60a15640059b": {"SeasonID": "46ea6166-4573-1128-9cea-60a15640059b", "NumberOfWins": 0, "NumberOfWinsWithPlacements": 11, "NumberOfGames": 87, "Rank": 0, "CapstoneWins": 0, "LeaderboardRank": 0, "CompetitiveTier": 0, "RankedRating": 0, "WinsByTier": {"0": 11}, "GamesNeededForRating": 0, "TotalWinsNeededForRank": 9}, "4cb622e1-4244-6da3-7276-8daaf1c01be2": {"SeasonID": "4cb622e1-4244-6da3-7276-8daaf1c01be2", "NumberOfWins": 0, "NumberOfWinsWithPlacements": 11, "NumberOfGames": 156, "Rank": 0, "CapstoneWins": 0, "LeaderboardRank": 0, "CompetitiveTier": 0, "RankedRating": 0, "WinsByTier": {"0": 11}, "GamesNeededForRating": 0, "TotalWinsNeededForRank": 9}, "52e9749a-429b-7060-99fe-4595426a0cf7": {"SeasonID": "52e9749a-429b-7060-99fe-4595426a0cf7", "NumberOfWins": 0, "NumberOfWinsWithPlacements": 2, "NumberOfGames": 56, "Rank": 0, "CapstoneWins": 0, "LeaderboardRank": 0, "CompetitiveTier": 0, "RankedRating": 0, "WinsByTier": {"0": 2}, "GamesNeededForRating": 0, "TotalWinsNeededForRank": 9}, "573f53ac-41a5-3a7d-d9ce-d6a6298e5704": {"SeasonID": "573f53ac-41a5-3a7d-d9ce-d6a6298e5704", "NumberOfWins": 0, "NumberOfWinsWithPlacements": 1, "NumberOfGames": 19, "Rank": 0, "CapstoneWins": 0, "LeaderboardRank": 0, "CompetitiveTier": 0, "RankedRating": 0, "WinsByTier": {"0": 1}, "GamesNeededForRating": 0, "TotalWinsNeededForRank": 9}, "97b6e739-44cc-ffa7-49ad-398ba502ceb0": {"SeasonID": "97b6e739-44cc-ffa7-49ad-398ba502ceb0", "NumberOfWins": 0, "NumberOfWinsWithPlacements": 1, "NumberOfGames": 26, "Rank": 0, "CapstoneWins": 0, "LeaderboardRank": 0, "CompetitiveTier": 0, "RankedRating": 0, "WinsByTier": {"0": 1}, "GamesNeededForRating": 0, "TotalWinsNeededForRank": 9}, "a16955a5-4ad0-f761-5e9e-389df1c892fb": {"SeasonID": "a16955a5-4ad0-f761-5e9e-389df1c892fb", "NumberOfWins": 0, "NumberOfWinsWithPlacements": 3, "NumberOfGames": 99, "Rank": 0, "CapstoneWins": 0, "LeaderboardRank": 0, "CompetitiveTier": 0, "RankedRating": 0, "WinsByTier": {"0": 3}, "GamesNeededForRating": 0, "TotalWinsNeededForRank": 9}, "ab57ef51-4e59-da91-cc8d-51a5a2b9b8ff": {"SeasonID": "ab57ef51-4e59-da91-cc8d-51a5a2b9b8ff", "NumberOfWins": 0, "NumberOfWinsWithPlacements": 1, "NumberOfGames": 18, "Rank": 0, "CapstoneWins": 0, "LeaderboardRank": 0, "CompetitiveTier": 0, "RankedRating": 0, "WinsByTier": {"0": 1}, "GamesNeededForRating": 0, "TotalWinsNeededForRank": 9}, "d929bc38-4ab6-7da4-94f0-ee84f8ac141e": {"SeasonID": "d929bc38-4ab6-7da4-94f0-ee84f8ac141e", "NumberOfWins": 0, "NumberOfWinsWithPlacements": 4, "NumberOfGames": 67, "Rank": 0, "CapstoneWins": 0, "LeaderboardRank": 0, "CompetitiveTier": 0, "RankedRating": 0, "WinsByTier": {"0": 4}, "GamesNeededForRating": 0, "TotalWinsNeededForRank": 9}}}, "seeding": {"TotalGamesNeededForRating": 5, "TotalGamesNeededForLeaderboard": 49, "CurrentSeasonGamesNeededForRating": 1, "SeasonalInfoBySeasonID": {}}, "spikerush": {"TotalGamesNeededForRating": 0, "TotalGamesNeededForLeaderboard": 0, "CurrentSeasonGamesNeededForRating": 1, "SeasonalInfoBySeasonID": {"46ea6166-4573-1128-9cea-60a15640059b": {"SeasonID": "46ea6166-4573-1128-9cea-60a15640059b", "NumberOfWins": 0, "NumberOfWinsWithPlacements": 32, "NumberOfGames": 54, "Rank": 0, "CapstoneWins": 0, "LeaderboardRank": 0, "CompetitiveTier": 0, "RankedRating": 0, "WinsByTier": {"0": 32}, "GamesNeededForRating": 0, "TotalWinsNeededForRank": 9}, "4cb622e1-4244-6da3-7276-8daaf1c01be2": {"SeasonID": "4cb622e1-4244-6da3-7276-8daaf1c01be2", "NumberOfWins": 0, "NumberOfWinsWithPlacements": 18, "NumberOfGames": 36, "Rank": 0, "CapstoneWins": 0, "LeaderboardRank": 0, "CompetitiveTier": 0, "RankedRating": 0, "WinsByTier": {"0": 18}, "GamesNeededForRating": 0, "TotalWinsNeededForRank": 9}, "573f53ac-41a5-3a7d-d9ce-d6a6298e5704": {"SeasonID": "573f53ac-41a5-3a7d-d9ce-d6a6298e5704", "NumberOfWins": 0, "NumberOfWinsWithPlacements": 7, "NumberOfGames": 9, "Rank": 0, "CapstoneWins": 0, "LeaderboardRank": 0, "CompetitiveTier": 0, "RankedRating": 0, "WinsByTier": {"0": 7}, "GamesNeededForRating": 0, "TotalWinsNeededForRank": 9}, "97b6e739-44cc-ffa7-49ad-398ba502ceb0": {"SeasonID": "97b6e739-44cc-ffa7-49ad-398ba502ceb0", "NumberOfWins": 0, "NumberOfWinsWithPlacements": 17, "NumberOfGames": 27, "Rank": 0, "CapstoneWins": 0, "LeaderboardRank": 0, "CompetitiveTier": 0, "RankedRating": 0, "WinsByTier": {"0": 17}, "GamesNeededForRating": 0, "TotalWinsNeededForRank": 9}, "a16955a5-4ad0-f761-5e9e-389df1c892fb": {"SeasonID": "a16955a5-4ad0-f761-5e9e-389df1c892fb", "NumberOfWins": 0, "NumberOfWinsWithPlacements": 5, "NumberOfGames": 11, "Rank": 0, "CapstoneWins": 0, "LeaderboardRank": 0, "CompetitiveTier": 0, "RankedRating": 0, "WinsByTier": {"0": 5}, "GamesNeededForRating": 0, "TotalWinsNeededForRank": 9}, "d929bc38-4ab6-7da4-94f0-ee84f8ac141e": {"SeasonID": "d929bc38-4ab6-7da4-94f0-ee84f8ac141e", "NumberOfWins": 0, "NumberOfWinsWithPlacements": 0, "NumberOfGames": 1, "Rank": 0, "CapstoneWins": 0, "LeaderboardRank": 0, "CompetitiveTier": 0, "RankedRating": 0, "WinsByTier": null, "GamesNeededForRating": 0, "TotalWinsNeededForRank": 0}}}, "unrated": {"TotalGamesNeededForRating": 0, "TotalGamesNeededForLeaderboard": 0, "CurrentSeasonGamesNeededForRating": 0, "SeasonalInfoBySeasonID": {"2a27e5d2-4d30-c9e2-b15a-93b8909a442c": {"SeasonID": "2a27e5d2-4d30-c9e2-b15a-93b8909a442c", "NumberOfWins": 0, "NumberOfWinsWithPlacements": 7, "NumberOfGames": 15, "Rank": 0, "CapstoneWins": 0, "LeaderboardRank": 0, "CompetitiveTier": 0, "RankedRating": 0, "WinsByTier": {"0": 7}, "GamesNeededForRating": 0, "TotalWinsNeededForRank": 9}, "3e47230a-463c-a301-eb7d-67bb60357d4f": {"SeasonID": "3e47230a-463c-a301-eb7d-67bb60357d4f", "NumberOfWins": 0, "NumberOfWinsWithPlacements": 16, "NumberOfGames": 24, "Rank": 0, "CapstoneWins": 0, "LeaderboardRank": 0, "CompetitiveTier": 0, "RankedRating": 0, "WinsByTier": {"0": 16}, "GamesNeededForRating": 0, "TotalWinsNeededForRank": 9}, "46ea6166-4573-1128-9cea-60a15640059b": {"SeasonID": "46ea6166-4573-1128-9cea-60a15640059b", "NumberOfWins": 0, "NumberOfWinsWithPlacements": 35, "NumberOfGames": 61, "Rank": 0, "CapstoneWins": 0, "LeaderboardRank": 0, "CompetitiveTier": 0, "RankedRating": 0, "WinsByTier": {"0": 35}, "GamesNeededForRating": 0, "TotalWinsNeededForRank": 9}, "4cb622e1-4244-6da3-7276-8daaf1c01be2": {"SeasonID": "4cb622e1-4244-6da3-7276-8daaf1c01be2", "NumberOfWins": 0, "NumberOfWinsWithPlacements": 68, "NumberOfGames": 127, "Rank": 0, "CapstoneWins": 0, "LeaderboardRank": 0, "CompetitiveTier": 0, "RankedRating": 0, "WinsByTier": {"0": 68}, "GamesNeededForRating": 0, "TotalWinsNeededForRank": 9}, "52e9749a-429b-7060-99fe-4595426a0cf7": {"SeasonID": "52e9749a-429b-7060-99fe-4595426a0cf7", "NumberOfWins": 0, "NumberOfWinsWithPlacements": 6, "NumberOfGames": 7, "Rank": 0, "CapstoneWins": 0, "LeaderboardRank": 0, "CompetitiveTier": 0, "RankedRating": 0, "WinsByTier": {"0": 6}, "GamesNeededForRating": 0, "TotalWinsNeededForRank": 9}, "573f53ac-41a5-3a7d-d9ce-d6a6298e5704": {"SeasonID": "573f53ac-41a5-3a7d-d9ce-d6a6298e5704", "NumberOfWins": 0, "NumberOfWinsWithPlacements": 33, "NumberOfGames": 55, "Rank": 0, "CapstoneWins": 0, "LeaderboardRank": 0, "CompetitiveTier": 0, "RankedRating": 0, "WinsByTier": {"0": 33}, "GamesNeededForRating": 0, "TotalWinsNeededForRank": 9}, "97b6e739-44cc-ffa7-49ad-398ba502ceb0": {"SeasonID": "97b6e739-44cc-ffa7-49ad-398ba502ceb0", "NumberOfWins": 0, "NumberOfWinsWithPlacements": 16, "NumberOfGames": 27, "Rank": 0, "CapstoneWins": 0, "LeaderboardRank": 0, "CompetitiveTier": 0, "RankedRating": 0, "WinsByTier": {"0": 16}, "GamesNeededForRating": 0, "TotalWinsNeededForRank": 9}, "a16955a5-4ad0-f761-5e9e-389df1c892fb": {"SeasonID": "a16955a5-4ad0-f761-5e9e-389df1c892fb", "NumberOfWins": 0, "NumberOfWinsWithPlacements": 83, "NumberOfGames": 163, "Rank": 0, "CapstoneWins": 0, "LeaderboardRank": 0, "CompetitiveTier": 0, "RankedRating": 0, "WinsByTier": {"0": 83}, "GamesNeededForRating": 0, "TotalWinsNeededForRank": 9}, "ab57ef51-4e59-da91-cc8d-51a5a2b9b8ff": {"SeasonID": "ab57ef51-4e59-da91-cc8d-51a5a2b9b8ff", "NumberOfWins": 0, "NumberOfWinsWithPlacements": 4, "NumberOfGames": 6, "Rank": 0, "CapstoneWins": 0, "LeaderboardRank": 0, "CompetitiveTier": 0, "RankedRating": 0, "WinsByTier": {"0": 4}, "GamesNeededForRating": 0, "TotalWinsNeededForRank": 9}, "d929bc38-4ab6-7da4-94f0-ee84f8ac141e": {"SeasonID": "d929bc38-4ab6-7da4-94f0-ee84f8ac141e", "NumberOfWins": 0, "NumberOfWinsWithPlacements": 16, "NumberOfGames": 34, "Rank": 0, "CapstoneWins": 0, "LeaderboardRank": 0, "CompetitiveTier": 0, "RankedRating": 0, "WinsByTier": {"0": 16}, "GamesNeededForRating": 0, "TotalWinsNeededForRank": 9}}}}, "LatestCompetitiveUpdate": {"MatchID": "e3b2bc5a-983b-4d47-8960-c46333cc7e9f", "MapID": "/Game/Maps/Bonsai/Bonsai", "SeasonID": "3e47230a-463c-a301-eb7d-67bb60357d4f", "MatchStartTime": 1651436655652, "TierAfterUpdate": 0, "TierBeforeUpdate": 0, "RankedRatingAfterUpdate": 0, "RankedRatingBeforeUpdate": 0, "RankedRatingEarned": 0, "RankedRatingPerformanceBonus": 0, "CompetitiveMovement": "MOVEMENT_UNKNOWN", "AFKPenalty": 0}, "IsLeaderboardAnonymized": false, "IsActRankBadgeHidden": false}